vidsrc/__init__.py
vidsrc/__init__.pyi
vidsrc/py.typed
vidsrc/vidsrc.cp314-win_amd64.pyd
vidsrc-2026.1.18.dist-info/licenses/LICENSE
vidsrc-2026.1.18.dist-info/METADATA
vidsrc-2026.1.18.dist-info/WHEEL
vidsrc-2026.1.18.dist-info/top_level.txt
vidsrc-2026.1.18.dist-info/RECORD
