Metadata-Version: 2.4
Name: vidsrc
Version: 2026.1.18
Summary: Video Frameserver for Numpy
Home-page: https://www.cgohlke.com
Author: Christoph Gohlke
Author-email: cgohlke@cgohlke.com
License: BSD-3-Clause
Project-URL: Bug Tracker, https://github.com/cgohlke/vidsrc/issues
Project-URL: Source Code, https://github.com/cgohlke/vidsrc
Platform: Windows
Classifier: Development Status :: 4 - Beta
Classifier: Intended Audience :: Science/Research
Classifier: Intended Audience :: Developers
Classifier: Topic :: Multimedia :: Video
Classifier: Operating System :: Microsoft :: Windows
Classifier: Programming Language :: C++
Classifier: Programming Language :: Python :: 3 :: Only
Classifier: Programming Language :: Python :: 3.11
Classifier: Programming Language :: Python :: 3.12
Classifier: Programming Language :: Python :: 3.13
Classifier: Programming Language :: Python :: 3.14
Requires-Python: >=3.11
License-File: LICENSE
Requires-Dist: numpy
Dynamic: author
Dynamic: author-email
Dynamic: classifier
Dynamic: description
Dynamic: description-content-type
Dynamic: home-page
Dynamic: license
Dynamic: license-file
Dynamic: platform
Dynamic: project-url
Dynamic: requires-dist
Dynamic: requires-python
Dynamic: summary
